setup_teardown/SetupTeardown.py
setup_teardown/__init__.py
setup_teardown-0.0.5.dist-info/LICENSE
setup_teardown-0.0.5.dist-info/METADATA
setup_teardown-0.0.5.dist-info/WHEEL
setup_teardown-0.0.5.dist-info/top_level.txt
setup_teardown-0.0.5.dist-info/RECORD
