Metadata-Version: 2.1
Name: setup-teardown
Version: 0.0.5
Summary: A setup/teardown context manager decorator for unit tests
Home-page: https://github.com/ahonnecke/setup-teardown-context-decorator
Author: Ashton Honnecke
Author-email: ashton@pixelstub.com
License: UNKNOWN
Project-URL: Bug Tracker, https://github.com/ahonnecke/setup-teardown-context-decorator/issues
Platform: UNKNOWN
Classifier: Programming Language :: Python :: 3
Classifier: License :: OSI Approved :: MIT License
Classifier: Operating System :: OS Independent
Requires-Python: >=3.6
License-File: LICENSE
